{
    "definition": {
        "description": "SYNC",
        "name": "SYNC018",
        "resource": "SYNC018",
        "type": "EVENT_DATA"
    },
    "structure": {
        "attributes": [
            {
                "code": "transactionalGuid",
                "name": "transactionalGuid",
                "type_definition": {
                    "type": "string"
                },
                "order": 1,
                "system": false,
                "required": false
            }
        ]
    }
}