{
    "walletEventHandler": [
        {
            "refId": "e-w-ta-send-engagement-request",
            "walletEvents": [
                {
                    "actions": [
                        {
                            "name": "submit",
                            "order": 1,
                            "parameter": [
                                {
                                    "method": "POST",
                                    "url": "/events" 
                                }
                            ]
                        }
                    ],
                    "postAction": "cd-794zs8jrs1bz9z9kvx-see-pis-7",
                    "refId": "e-w-ta-send-engagement-request"  
                }
            ]
        }
    ] 
}