{
    "walletEventHandler": [
        {
            "refId": "e-w-trial-admin-navig-to-49-sp1",
            "walletEvents": [
                {
                    "actions": [
                        {
                            "name": "submit",
                            "order": 1,
                            "parameter": [
                                {
                                    "method": "DETAILS",
                                    "url": ""
                                }
                            ]
                        }
                    ],
                    "postAction": "cd-j8dk0pwzbdvgr3dpkojzpl499sp1",
                    "refId": "e-w-trial-admin-navig-to-49-sp1"
                }
            ]
        }
    ]
}